{
  "avaliacoes": [
    {
      "data": "2024-06-23T10:20:30Z",
      "nome": "Cliente 1",
      "nota": 5,
      "avaliacao": "Excelente serviço!"
    },
    {
      "data": "2024-06-24T11:22:33Z",
      "nome": "Cliente 2",
      "nota": 4,
      "avaliacao": "Muito bom, mas pode melhorar."
    },
    {
      "data": "2024-06-25T12:24:36Z",
      "nome": "Cliente 3",
      "nota": 3,
      "avaliacao": "Foi satisfatório."
    },
    {
      "data": "2024-06-24T18:20:55.923Z",
      "nome": "Heron",
      "nota": 4,
      "avaliacao": "aaaaaaa bbb"
    },
    {
      "data": "2024-06-25T00:11:42.315Z",
      "nome": "heron",
      "nota": 5,
      "avaliacao": "avaliacao teste"
    }
  ]
}